capnweb/__init__.py
capnweb/certs.py
capnweb/client.py
capnweb/core/__init__.py
capnweb/core/hooks.py
capnweb/core/mapper.py
capnweb/core/parser.py
capnweb/core/payload.py
capnweb/core/pipeline.py
capnweb/core/resume.py
capnweb/core/serializer.py
capnweb/core/session.py
capnweb/core/stubs.py
capnweb/error.py
capnweb/protocol/__init__.py
capnweb/protocol/ids.py
capnweb/protocol/wire.py
capnweb/py.typed
capnweb/server.py
capnweb/transport/__init__.py
capnweb/transport/transports.py
capnweb/transport/webtransport.py
capnweb/types.py
py_capnweb-0.5.0.dist-info/WHEEL
py_capnweb-0.5.0.dist-info/METADATA
py_capnweb-0.5.0.dist-info/RECORD
