Metadata-Version: 2.3
Name: py-capnweb
Version: 0.5.0
Summary: Python implementation of the Cap'n Web protocol
Keywords: rpc,capabilities,capnweb,websockets,http3
Author: Cap'n Web Contributors
License: MIT OR Apache-2.0
Classifier: Development Status :: 3 - Alpha
Classifier: Intended Audience :: Developers
Classifier: License :: OSI Approved :: MIT License
Classifier: License :: OSI Approved :: Apache Software License
Classifier: Programming Language :: Python :: 3
Classifier: Programming Language :: Python :: 3.11
Classifier: Programming Language :: Python :: 3.12
Classifier: Programming Language :: Python :: 3.13
Classifier: Topic :: Internet :: WWW/HTTP
Classifier: Topic :: Software Development :: Libraries :: Python Modules
Requires-Dist: aiohttp>=3.9.0
Requires-Dist: websockets>=12.0
Requires-Dist: typing-extensions>=4.9.0
Requires-Dist: cryptography>=46.0.2
Requires-Dist: aioquic>=1.2.0
Requires-Python: >=3.11
Project-URL: Changelog, https://github.com/abilian/py-capnweb/blob/main/CHANGES.md
Project-URL: Documentation, https://github.com/abilian/py-capnweb#readme
Project-URL: Homepage, https://github.com/abilian/py-capnweb
Project-URL: Issues, https://github.com/abilian/py-capnweb/issues
Project-URL: Repository, https://github.com/abilian/py-capnweb.git
